Workbook

Sheet Summary
B2: FRONTAL · QUALITATIVE GTM AUDIT
B3: Your go-to-market engine — scored.
B4: 60-minute audit across seven layers: Brand → Data → Signal → RevOps → Outbound → Ads → Sales Process. Maturity scored 0–4 per dimension.
B6: CLIENT | I6: MATURITY SCORE BY LAYER
B7: Company | I7: Layer | J7: Score | K7: % of max
B8: ARR / revenue range | I8: 1. Brand & Positioning | J8: ='1. Brand & Positioning'!I13 -> 0 | K8: =IFERROR(J8/32,0) -> 0
B9: Employees | I9: 2. Data Layer | J9: ='2. Data Layer'!I13 -> 0 | K9: =IFERROR(J9/32,0) -> 0
B10: Primary industry | I10: 3. Signal Layer | J10: ='3. Signal Layer'!I13 -> 0 | K10: =IFERROR(J10/32,0) -> 0
B11: Audit date | I11: 4. Execution — RevOps | J11: ='4. Execution — RevOps'!I13 -> 0 | K11: =IFERROR(J11/32,0) -> 0
B12: Frontal lead(s) | I12: 5. Execution — Outbound | J12: ='5. Execution — Outbound'!I13 -> 0 | K12: =IFERROR(J12/32,0) -> 0
B13: Client stakeholders | I13: 6. Execution — Ads | J13: ='6. Execution — Ads'!I13 -> 0 | K13: =IFERROR(J13/32,0) -> 0
I14: 7. Sales Process | J14: ='7. Sales Process'!I13 -> 0 | K14: =IFERROR(J14/32,0) -> 0
I15: TOTAL | J15: =SUM(J8:J14) -> 0 | K15: =J15/224 -> 0
B18: OVERALL MATURITY BAND
B19: =IF(J15=0,"— score the audit to see the band —",IF(J15<=56,"FOUNDATION",IF(J15<=112,"BUILDING",IF(J15<=168,"SCALING","COMPOUNDING")))) -> — score the audit to see the band — | G19: =IF(J15=0,"Fill the audit tabs to generate an overall maturity read.",IF(J15<=56,"No GTM infrastructure. Founder-led, scattered. Start with the Data Layer.",IF(J15<=112,"Tools in place, not wired together. Priority is Data + RevOps fundamentals.",IF(J15<=168,"Systems forming. Room to deepen signal capture, ads, and multi-channel execution.","System-led GTM. Opportunity for advanced plays — ABM, Content Engine, AI agents.")))) -> Fill the audit tabs to generate an overall maturity read.
B21: 0–56 | C21: FOUNDATION | D21: No system. Founder-led, scattered.
B22: 57–112 | C22: BUILDING | D22: Tools in place, not wired.
B23: 113–168 | C23: SCALING | D23: Systems working, room to deepen.
B24: 169–224 | C24: COMPOUNDING | D24: Full system-led GTM. Advanced plays running.
B27: HEADLINE TAKEAWAYS · fill this during the readback
B28: Top 3 strengths
B29: Top 3 gaps
B30: Quick wins (30 days)
B31: Strategic moves (90 days)
B32: Red flags / risks

Sheet 1. Brand & Positioning
A1: 1. BRAND & POSITIONING
A2: The left side of the chain. Diagnoses whether the client is positioned so that data, signal, and execution work.
A4: # | B4: Dimension | C4: Diagnostic probe | D4: Level 0 | E4: Level 1 | F4: Level 2 | G4: Level 3 | H4: Level 4 | I4: Score | J4: Quant metric + benchmark | K4: Actual | L4: Notes / evidence
A5: B1 | B5: ICP Definition Clarity | C5: How clearly defined is the Ideal Customer Profile? | D5: No defined ICP. Selling to anyone with a pulse. | E5: Rough segment only (e.g., 'B2B SaaS founders'). | F5: Documented ICP with firmographic filters. | G5: Multi-tier ICP (Tier 1/2/3) with clear fit criteria. | H5: ICP validated against closed-won data, refreshed quarterly, with anti-fit exclusions.
A6: B2 | B6: Positioning & One-Liner | C6: How sharp is the value proposition and differentiation? | D6: Generic claims ('we help companies grow'). | E6: Feature-led pitch, undifferentiated. | F6: Clear category + outcome, weak differentiation. | G6: Differentiated position, supported by proof points. | H6: Owned narrative (POV-led / category-shaping), strong competitive moat.
A7: B3 | B7: Website — Conversion Readiness | C7: Does the website convert traffic into pipeline? | D7: Brochure site, no CTAs or lead capture. | E7: Basic contact form, single CTA. | F7: Segmented landing pages, lead capture, live chat. | G7: Personalised / account-aware site experience. | H7: Signal-driven site (visitor de-anon + routed CTAs + intent personalisation). | J7: Homepage→demo CVR (target >2%)
A8: B4 | B8: Social Proof Library | C8: How robust is the social proof arsenal? | D8: No logos, no case studies. | E8: Logo wall only. | F8: 2–3 case studies + testimonials. | G8: 10+ case studies mapped to ICP segments with metrics. | H8: Continuous case-study engine + peer-review proof (G2, awards, analyst mentions). | J8: # case studies live
A9: B5 | B9: Founder / Exec LinkedIn Presence | C9: Are senior leaders publishing consistently on LinkedIn? | D9: Dormant profiles. | E9: Occasional posts, no cadence. | F9: Regular posting (~1x/week), some engagement. | G9: Consistent cadence (3+/week), 5K+ followers. | H9: Founder-led content as primary TOFU. 25K+ followers. Meetings booked directly from content. | J9: Posts/week + follower count
A10: B6 | B10: Company Content Cadence | C10: What does the content engine look like beyond social? | D10: No content production. | E10: Ad-hoc blog posts. | F10: Monthly blog / newsletter. | G10: Multi-format program (blog + podcast + video + newsletter) on schedule. | H10: Content atomised from sales conversations, distributed across all channels, tied to pipeline. | J10: Content pieces/month
A11: B7 | B11: Visual Brand System | C11: Is the brand visually coherent across all surfaces? | D11: No brand guidelines, inconsistent design. | E11: Basic logo and color, ad-hoc design. | F11: Brand guidelines document, mostly followed. | G11: Design system with templates for social, sales, web. | H11: Mature brand identity, recognised in category, design ops in place.
A12: B8 | B12: Category Narrative | C12: Is the company defining, defending, or following a category? | D12: No awareness of category positioning. | E12: Generic category fit ('we're a CRM'). | F12: Differentiated niche within a category. | G12: Actively framing a sub-category with owned vocabulary. | H12: Category creator — analysts and market reference them.
A13: SECTION TOTAL | I13: =SUM(I5:I12) -> 0 | J13: out of 32 max

Sheet 2. Data Layer
A1: 2. DATA LAYER
A2: Your TAM cleaned, enriched, scored. Every account and contact mapped, verified, ready to activate.
A4: # | B4: Dimension | C4: Diagnostic probe | D4: Level 0 | E4: Level 1 | F4: Level 2 | G4: Level 3 | H4: Level 4 | I4: Score | J4: Quant metric + benchmark | K4: Actual | L4: Notes / evidence
A5: D1 | B5: CRM as Source of Truth | C5: Is the CRM the definitive record for accounts and contacts? | D5: No CRM, or CRM not used. | E5: CRM exists but duplicates, missing fields, ignored. | F5: CRM used by sales but not synced to marketing/CS. | G5: Central CRM with enforced hygiene, dedupe rules, mandatory fields. | H5: Dual-CRM architecture (mkt + sales) or single source with full bi-directional sync, weekly audit. | J5: % opps with mandatory fields populated (target >90%)
A6: D2 | B6: TAM Mapping | C6: Is the full addressable market mapped and in the CRM? | D6: No TAM defined. | E6: Rough count ('there are 10K companies like this'). | F6: TAM list built, but static and stale. | G6: TAM mapped, segmented by tier, refreshed quarterly. | H6: Full scored TAM in CRM (fit + tier), living list, continuous enrichment. | J6: # accounts in TAM
A7: D3 | B7: Account Firmographic Enrichment | C7: How deep is the firmographic data layer on each account? | D7: Name and domain only. | E7: Revenue range and headcount (manual). | F7: Enriched from a single source (Apollo or ZoomInfo). | G7: Multi-source waterfall (Clay + LinkedIn + secondary). | H7: Custom data points (funding, tech stack, growth signals) auto-refreshed. | J7: % accounts with ≥10 firmographic fields
A8: D4 | B8: Contact Enrichment — Email + Phone Waterfall | C8: How reliable is contact data for outbound? | D8: Scraped emails, high bounce rate. | E8: Single-source emails, some verification. | F8: Verified emails (LeadMagic / BounceBan) on outbound list. | G8: Waterfall enrichment (3+ providers) with validation step. | H8: Full waterfall (email + mobile) with re-verification on every outbound batch. | J8: Bounce rate % (target <2%)
A9: D5 | B9: ICP Fit Scoring | C9: Is every account/contact scored for ICP fit? | D9: No scoring — all accounts treated equal. | E9: Manual tiering by rep gut-feel. | F9: Basic rule-based ICP score (industry + size). | G9: Multi-factor score (firmographics + tech + intent) recalculated regularly. | H9: ML-based scoring calibrated against closed-won, surfaced in CRM.
A10: D6 | B10: Cross-Tool Data Sync | C10: Does data flow cleanly across the GTM stack? | D10: Tools don't talk to each other. | E10: Manual CSV exports between tools. | F10: Some native integrations (CRM ↔ sequencer). | G10: Bi-directional sync across CRM, sequencer, ads, enrichment. | H10: Full orchestration layer (n8n/Make/Zapier) with monitoring and error handling.
A11: D7 | B11: Data Coverage vs TAM | C11: What % of the TAM is fully enriched and actionable? | D11: <25% of TAM has workable data. | E11: 25–50%. | F11: 50–75%. | G11: 75–90% with verified contacts. | H11: 90%+ with decision-maker coverage and ongoing refresh. | J11: % TAM enriched
A12: D8 | B12: Data Decay Management | C12: How is data kept fresh against 22%/yr natural decay? | D12: No refresh — data decays unmanaged. | E12: Annual re-enrichment. | F12: Quarterly re-enrichment. | G12: Monthly re-enrichment + job-change tracking. | H12: Real-time signals — job/role/company changes trigger CRM updates. | J12: Re-enrichment cadence (days)
A13: SECTION TOTAL | I13: =SUM(I5:I12) -> 0 | J13: out of 32 max

Sheet 3. Signal Layer
A1: 3. SIGNAL LAYER
A2: Buying signals, intent, and account scoring. Behavioural triggers wired into the CRM.
A4: # | B4: Dimension | C4: Diagnostic probe | D4: Level 0 | E4: Level 1 | F4: Level 2 | G4: Level 3 | H4: Level 4 | I4: Score | J4: Quant metric + benchmark | K4: Actual | L4: Notes / evidence
A5: S1 | B5: Buying Intent Signals (3rd Party) | C5: Are 3rd-party intent signals captured and wired into the CRM? | D5: No intent data. | E5: G2 reviews monitored manually. | F5: Single intent source (Bombora or 6sense) in CRM. | G5: Multi-source intent (G2 + Bombora + 6sense) with topic tracking. | H5: Intent composited with fit score, triggering account-level actions.
A6: S2 | B6: Website Visitor De-anonymization | C6: Are anonymous visitors being identified company-by-company? | D6: GA only, no identification. | E6: Basic analytics (GA4), no identification. | F6: Email-level tracking (HubSpot known contacts). | G6: De-anon solution (RB2B / Warmly / Vector) identifying companies. | H6: De-anon + contact enrichment + auto-routing to outbound, ads, and CSM. | J6: % visitors de-anonymized
A7: S3 | B7: LinkedIn Engagement Capture | C7: Are LinkedIn post engagers and profile visitors captured? | D7: LinkedIn engagement ignored. | E7: Engagers manually reviewed by founder. | F7: Post engagers scraped (LeadMagic) but not actioned. | G7: Post + profile visitor capture, enriched, routed by ICP fit. | H7: Every engagement triggers a personalised play. Full engagement pipeline.
A8: S4 | B8: Trigger Signals — Hiring / Funding / Tech | C8: Are leading-indicator signals monitored? | D8: No signal monitoring. | E8: Manual news scanning. | F8: Single signal type (e.g., funding announcements). | G8: Multi-signal monitoring (Trigify / PredictLeads / HG Insights). | H8: All signals composited, scored by urgency, triggering timely outbound.
A9: S5 | B9: Account Scoring — Fit × Intent | C9: Are accounts scored by both fit AND intent? | D9: No scoring. | E9: Fit score only. | F9: Fit + basic intent (e.g., website visits). | G9: Composite score (fit × multi-signal intent). | H9: Dynamic score refreshed on every signal event, visible in CRM.
A10: S6 | B10: Lead-to-Account Matching | C10: Are inbound leads matched to the correct account automatically? | D10: Leads dumped as standalone contacts. | E10: Manual matching by rep. | F10: Basic fuzzy match on domain. | G10: Automated lead-to-account matching with account-owner routing. | H10: Full matching + de-duping + cross-object relationship mapping.
A11: S7 | B11: Signal-to-Action Routing | C11: When a signal fires, does it trigger an action automatically? | D11: Signals detected but no action taken. | E11: Manual review and follow-up. | F11: Signals alert reps (Slack). | G11: Signals auto-enrol contact into the right sequence. | H11: Multi-channel signal orchestration (sequence + ads + CSM outreach). | J11: Time signal→action (target <1hr)
A12: S8 | B12: Inbound Lead Scoring & Routing | C12: How are inbound leads scored and routed? | D12: All leads treated equal, one inbox. | E12: Basic round-robin to reps. | F12: ICP filter before rep routing. | G12: Fit + intent score determines SLA tier (hot/warm/nurture). | H12: Full speed-to-lead automation, enriched briefing to rep before first touch. | J12: Lead response time (target <5 min)
A13: SECTION TOTAL | I13: =SUM(I5:I12) -> 0 | J13: out of 32 max

Sheet 4. Execution — RevOps
A1: 4. EXECUTION — REVOPS
A2: The central engine. Pipeline ops, routing, SLAs, dashboards, workflow automation.
A4: # | B4: Dimension | C4: Diagnostic probe | D4: Level 0 | E4: Level 1 | F4: Level 2 | G4: Level 3 | H4: Level 4 | I4: Score | J4: Quant metric + benchmark | K4: Actual | L4: Notes / evidence
A5: R1 | B5: Pipeline Stages & Conversion | C5: Are pipeline stages defined and conversion tracked? | D5: Stages not defined or inconsistent. | E5: Basic stages, conversion tracked ad-hoc. | F5: Stages documented, conversion rates reviewed monthly. | G5: Exit criteria per stage, conversion tracked by segment/rep. | H5: Stage conversion benchmarks with deviation alerts, deal-desk governance. | J5: Stage conversion rates
A6: R2 | B6: Lead Routing & Speed-to-Lead | C6: How fast and accurate is inbound lead routing? | D6: Inbox dumping, no routing. | E6: Daily manual assignment. | F6: Round-robin with basic rules. | G6: Signal-based routing (territory + account tier + intent). | H6: Sub-5-min SLA with auto-enrichment and rep briefing. | J6: Median lead response time
A7: R3 | B7: Meeting & Scheduling Ops | C7: Is the meeting booking flow friction-free and context-rich? | D7: Back-and-forth email scheduling. | E7: Basic Calendly links. | F7: Routed scheduling with reminders. | G7: Chili Piper / Calendly routing by owner/tier with prep docs. | H7: Full calendar ops: pre-meeting research auto-generated + reminders + post-meeting sync.
A8: R4 | B8: Handoff SLAs — Marketing → Sales → CS | C8: Are handoffs governed by SLAs? | D8: No SLAs; leads and deals fall through cracks. | E8: Informal handoffs. | F8: Documented handoff criteria. | G8: Tracked SLAs with alerts on breach. | H8: Automated handoff workflows with full context transfer.
A9: R5 | B9: Dashboards & Reporting | C9: What operational dashboards exist? | D9: No dashboards; numbers pulled manually. | E9: Spreadsheet-based reports. | F9: CRM-native dashboards (pipeline). | G9: Multi-dimension dashboards (pipeline, velocity, conversion, CAC). | H9: Executive BI layer (cross-tool) with predictive / forecasting views.
A10: R6 | B10: Workflow Automation Library | C10: How mature is the automation layer? | D10: Nothing automated. | E10: A few Zapier tasks. | F10: Documented workflows in Zapier / Make. | G10: Robust n8n / Make library with version control. | H10: AI agents embedded in workflows, full observability, error handling.
A11: R7 | B11: Renewal & Expansion Pipeline | C11: Is the post-sale motion managed as a proper pipeline? | D11: No renewal tracking. | E11: Spreadsheet of renewal dates. | F11: Renewal pipeline in CRM with stage logic. | G11: Forecasted renewals + expansion plays triggered by usage/signals. | H11: Full CS ops motion — health scoring, QBRs, expansion automation. | J11: NRR %
A12: R8 | B12: Reply Classification & Disposition | C12: Are outbound replies classified and routed? | D12: Reps sort manually. | E12: Basic rules (interested / not interested). | F12: Sequencer-native reply detection. | G12: AI-classified replies (positive / objection / not now). | H12: Replies auto-routed to right flow (meeting / objection handling / nurture).
A13: SECTION TOTAL | I13: =SUM(I5:I12) -> 0 | J13: out of 32 max

Sheet 5. Execution — Outbound
A1: 5. EXECUTION — OUTBOUND
A2: Outbound as a system: deliverability, cadence, personalisation, LinkedIn, multi-channel, content, AI agents.
A4: # | B4: Dimension | C4: Diagnostic probe | D4: Level 0 | E4: Level 1 | F4: Level 2 | G4: Level 3 | H4: Level 4 | I4: Score | J4: Quant metric + benchmark | K4: Actual | L4: Notes / evidence
A5: O1 | B5: Email Deliverability Infrastructure | C5: Is the sending infrastructure healthy and scalable? | D5: Single domain, no warmup, blacklisted. | E5: 1 domain, a few mailboxes, ad-hoc warmup. | F5: 2–5 domains, mailboxes warmed ≥30 days, SPF/DKIM/DMARC set. | G5: Dedicated infra (5+ domains, 3 mailboxes/domain, continuous warmup). | H5: Inbox placement monitoring (GlockApps), reputation alerts, multi-provider redundancy. | J5: Inbox placement % (target >85%); # domains; # mailboxes
A6: O2 | B6: Sequencer Setup & Cadence | C6: How sophisticated is the outbound sequencer? | D6: No sequencer; manual sends. | E6: Basic sequences (1 cadence for all). | F6: Multiple sequences by segment. | G6: ICP + signal-specific sequences with A/B testing. | H6: Fully orchestrated sequences across channels with liquid variables and trigger branches. | J6: Reply rate % (target 2–5% cold, 10%+ warm)
A7: O3 | B7: Personalisation Depth | C7: How personalised is outbound messaging at scale? | D7: 'Hi [first name]' only. | E7: Company name + generic hook. | F7: Role-based templates. | G7: AI-generated personalisation (Clay + Claude) on every send. | H7: Multi-variable relevance (signal + persona + case-study match) — near-1:1 quality at scale. | J7: Positive reply rate by segment
A8: O4 | B8: LinkedIn Outbound Operations | C8: How is LinkedIn outbound structured? | D8: No LinkedIn outreach. | E8: Manual connect messages from founder. | F8: HeyReach / Expandi / Lemlist with single cadence. | G8: Multi-account LinkedIn outbound, ICP-filtered, tied to CRM. | H8: LinkedIn + email orchestration, engagement-triggered, ICP-scored. | J8: LinkedIn reply rate %
A9: O5 | B9: Multi-Channel Orchestration | C9: Are outbound channels coordinated across email, LinkedIn, and ads? | D9: Channels run independently, no coordination. | E9: Email + LinkedIn run in parallel by same rep. | F9: Documented sequence across email + LinkedIn. | G9: Email + LinkedIn + ads hitting same ICP accounts in coordinated windows. | H9: Full orchestration — signals trigger cross-channel plays, all in one system.
A10: O6 | B10: Testing & Iteration Cadence | C10: How systematically is outbound tested and improved? | D10: No testing. Same templates forever. | E10: Occasional rewrites when results dip. | F10: Subject-line / opener A/B tests run ad-hoc. | G10: Weekly performance review with documented test backlog. | H10: Continuous test program — multi-variate on copy, offer, cadence, persona — feeding a learnings doc. | J10: Tests run / month
A11: O7 | B11: Content Engine (Advanced) | C11: Is there a content engine feeding outbound and nurture? | D11: No content support for outbound. | E11: Reps send links to old blog posts. | F11: Monthly asset supports campaigns. | G11: Founder-led content repurposed across email, LinkedIn, ads. | H11: Full Content-as-a-Service: sales conversations → content → ads/outbound/nurture in a closed loop.
A12: O8 | B12: AI Agents / GTM Ops (Advanced) | C12: Are AI agents embedded in the GTM stack? | D12: No AI in GTM workflows. | E12: Point-use ChatGPT for email drafting. | F12: Clay + Claude integration for enrichment/personalisation. | G12: Custom agents in workflows (enrichment, routing, classification). | H12: AI agents running autonomous plays — research, outbound drafts, reply handling, in background.
A13: SECTION TOTAL | I13: =SUM(I5:I12) -> 0 | J13: out of 32 max

Sheet 6. Execution — Ads
A1: 6. EXECUTION — ADS
A2: Paid as a coordinated layer: strategy, channel mix, ABM, signal-triggered, creative, landing pages, attribution.
A4: # | B4: Dimension | C4: Diagnostic probe | D4: Level 0 | E4: Level 1 | F4: Level 2 | G4: Level 3 | H4: Level 4 | I4: Score | J4: Quant metric + benchmark | K4: Actual | L4: Notes / evidence
A5: A1 | B5: Paid Strategy & Role in Pipeline | C5: Is there a defined role for paid in the GTM mix? | D5: No paid. Or 'we tried it, didn't work.' | E5: Ad-hoc paid campaigns, no strategy. | F5: Paid runs for brand or lead-gen, measured separately. | G5: Paid has a defined role (demand gen, demand capture, ABM) with targets per channel. | H5: Paid is integrated into the GTM system — budget tied to pipeline targets, feeding outbound and sales. | J5: % pipeline attributed to paid
A6: A2 | B6: Channel Mix & Budget Allocation | C6: Which paid channels are active, and how is budget allocated? | D6: One channel, no strategy. | E6: 2+ channels, budget by gut feel. | F6: Multi-channel (LinkedIn, Google, Meta) with basic budget logic. | G6: Budget allocated by CAC/ROAS per channel, reviewed monthly. | H6: Portfolio approach — brand, demand capture, ABM, retargeting each with a role and measured ROAS. | J6: Monthly paid spend + channel split
A7: A3 | B7: ABM / Account-Based Ads | C7: Are ads targeting specific high-value accounts? | D7: No account targeting — broad audiences only. | E7: Lookalike audiences from customer list. | F7: ABM audience from target list (top 200 accounts). | G7: ABM ads tied to CRM list, refreshed on new accounts, segmented by tier. | H7: Signal-triggered ABM — ad spend ramps when an account shows intent. | J7: # target accounts reached by ads
A8: A4 | B8: Signal-Triggered & Retargeting Flows | C8: Do ads respond to behaviour and intent signals? | D8: Static ads, no retargeting. | E8: Basic website retargeting (all visitors). | F8: Retargeting segmented by page / stage. | G8: Retargeting tied to CRM stage + signal source (funding, hiring, intent). | H8: Full signal loop — ads fire on specific triggers, content changes by trigger type, synced with outbound and CSM. | J8: Retargeting CTR vs cold CTR
A9: A5 | B9: Creative & Messaging Quality | C9: How strong is the creative system? | D9: Generic stock imagery, product screenshots. | E9: Occasional bespoke creative, no system. | F9: Brand-aligned creative, produced in batches. | G9: Creative system with templates, variants per persona, regular refresh. | H9: Creative atomised from sales conversations and content — persona-matched, tested, refreshed weekly. | J9: # active creative variants
A10: A6 | B10: Landing Page Experience | C10: Where does ad traffic land, and how well does it convert? | D10: Homepage only. | E10: Generic landing page, single CTA. | F10: Campaign-specific landing pages. | G10: Segmented landing pages by persona or industry with clear CTAs. | H10: Personalised / account-aware landing pages (dynamic variables, named social proof). | J10: Ad LP conversion rate %
A11: A7 | B11: Attribution & Measurement | C11: Is paid attribution trustworthy and actionable? | D11: No tracking beyond platform metrics. | E11: Single-touch (last click) attribution. | F11: UTM discipline + CRM source tracking. | G11: Multi-touch attribution model, reviewed monthly, feeds channel decisions. | H11: Blended CAC + pipeline attribution across channels, integrated with CRM forecast. | J11: CAC by channel; CAC payback months
A12: A8 | B12: Integration with Outbound & CRM | C12: Do ads and outbound work together, or in parallel silos? | D12: Ads and outbound operate independently. | E12: Shared ICP list, no coordination. | F12: Ads warm accounts before outbound touches them. | G12: Same account list hit by ads + outbound + content in coordinated windows. | H12: Full orchestration — signals route simultaneously to ads, outbound, and CSM. One pipeline, three channels.
A13: SECTION TOTAL | I13: =SUM(I5:I12) -> 0 | J13: out of 32 max

Sheet 7. Sales Process
A1: 7. SALES PROCESS
A2: The right side of the chain. Sales team structure, qualification, forecast, deal discipline.
A4: # | B4: Dimension | C4: Diagnostic probe | D4: Level 0 | E4: Level 1 | F4: Level 2 | G4: Level 3 | H4: Level 4 | I4: Score | J4: Quant metric + benchmark | K4: Actual | L4: Notes / evidence
A5: SP1 | B5: Sales Team Structure | C5: How is the sales team structured relative to motion and scale? | D5: Founder is only seller. | E5: Founder + 1 generalist. | F5: Defined SDR / AE split. | G5: SDRs (inbound + outbound) + AEs (commercial + enterprise) + ops support. | H5: Full motion: SDRs, AEs, SEs, CS, RevOps, enablement.
A6: SP2 | B6: Qualification Framework | C6: Is there a documented and enforced qualification methodology? | D6: No framework — reps wing it. | E6: Informal BANT. | F6: Documented BANT/MEDDIC, inconsistently applied. | G6: MEDDIC / MEDDPICC enforced, fields in CRM. | H6: Qualification scoring drives forecast confidence and deal-desk review.
A7: SP3 | B7: Call Recording & Coaching | C7: Are sales calls recorded, analysed, and used for coaching? | D7: No recording. | E7: Gong / Fireflies installed, rarely reviewed. | F7: Recordings reviewed ad-hoc in 1:1s. | G7: Scorecard-driven coaching, weekly review cadence. | H7: AI insights from call analytics feed back into pipeline + sequences + content. | J7: Calls coached / rep / month
A8: SP4 | B8: Proposal / Quote-to-Cash | C8: How structured is the proposal-to-signature flow? | D8: Ad-hoc PDFs and email trails. | E8: Basic proposal template. | F8: CPQ for standard deals. | G8: CPQ + approval workflows + e-sign integrated with CRM. | H8: Full quote-to-cash automation with discount governance and auto-provisioning.
A9: SP5 | B9: Pipeline Hygiene & Forecast Accuracy | C9: Is pipeline data trustworthy and is forecast accurate? | D9: Pipeline is a mess, no forecasting. | E9: Weekly review, high variance vs actuals. | F9: Monthly forecast with ~60–70% accuracy. | G9: Weighted forecast by stage with 80%+ accuracy, deal inspection cadence. | H9: Predictive AI forecasting with sub-10% variance, deal-desk governance. | J9: Forecast accuracy % (target ≥85%)
A10: SP6 | B10: Win/Loss Analysis & Closed-Loss Reactivation | C10: Are losses understood and re-engaged when signals change? | D10: Losses never analysed. | E10: Informal post-mortems on big deals. | F10: Documented win/loss reasons in CRM. | G10: Quarterly win/loss program with interviews, feedback to product/marketing. | H10: Closed-lost re-engagement flows triggered by signals (tech / personnel / funding change).
A11: SP7 | B11: CRM Deal Management Discipline | C11: How disciplined is CRM data entry by reps? | D11: Reps barely use CRM. | E11: Sporadic updates. | F11: Required fields enforced, activities partially logged. | G11: Every activity auto-logged (email/call/meeting), MEDDIC fields maintained. | H11: CRM is single source; AI summarises calls/emails into CRM automatically. | J11: % activities auto-captured
A12: SP8 | B12: Champion Tracking & Buying Committee Mapping | C12: Are champions and buying committees mapped and tracked? | D12: Only one contact per account. | E12: Primary contact + one backup. | F12: Key personas documented in notes. | G12: Buying committee mapped in CRM (champion / DM / economic buyer / blockers). | H12: Multi-threaded with champion-moved tracking (Fireflies / Clay alerts on job changes).
A13: SECTION TOTAL | I13: =SUM(I5:I12) -> 0 | J13: out of 32 max
